apaai/__init__.py
apaai/api.py
apaai/client.py
apaai/types.py
apaai/utils.py
apaai-0.2.1.dist-info/METADATA
apaai-0.2.1.dist-info/WHEEL
apaai-0.2.1.dist-info/top_level.txt
apaai-0.2.1.dist-info/RECORD
