Metadata-Version: 2.4
Name: apaai
Version: 0.2.1
Summary: APAAI Protocol Python SDK — Action → Policy → Evidence
Author: apaAI Labs
License-Expression: Apache-2.0
Project-URL: Homepage, https://apaaiprotocol.org
Project-URL: Repository, https://github.com/apaAI-Labs/apaai-protocol
Keywords: apaai,protocol,agent,governance,audit,evidence
Classifier: Development Status :: 4 - Beta
Classifier: Intended Audience :: Developers
Classifier: Programming Language :: Python :: 3
Classifier: Programming Language :: Python :: 3.9
Classifier: Programming Language :: Python :: 3.10
Classifier: Programming Language :: Python :: 3.11
Classifier: Programming Language :: Python :: 3.12
Classifier: Topic :: Software Development :: Libraries :: Python Modules
Classifier: Topic :: System :: Monitoring
Requires-Python: >=3.9
Requires-Dist: requests>=2.31.0
